rdppy/__init__.py
rdppy/rdp.py
rdppy-0.0.2.dist-info/LICENSE.txt
rdppy-0.0.2.dist-info/METADATA
rdppy-0.0.2.dist-info/WHEEL
rdppy-0.0.2.dist-info/top_level.txt
rdppy-0.0.2.dist-info/RECORD
