Metadata-Version: 2.1
Name: rdppy
Version: 0.0.2
Summary: Implementation of the Ramer–Douglas–Peucker algorithm
Home-page: https://github.com/avitase/rdppy
Author: Nis Meinert
Author-email: nis.meinert@gmail.com
License: UNKNOWN
Project-URL: Bug Tracker, https://github.com/avitase/rdppy/issues
Platform: UNKNOWN
Classifier: Programming Language :: Python :: 3
Classifier: License :: OSI Approved :: MIT License
Classifier: Operating System :: OS Independent
Requires-Python: >=3.8
License-File: LICENSE.txt
Requires-Dist: numpy
